Workbook
Name Beta0_0: Sheet1!$B$19
Name Beta0_1: Sheet1!$C$19
Name Beta1: Sheet1!$B$12
Name Beta2: Sheet1!$B$13
Name iext_0: Sheet1!$B$18
Name iext_1: Sheet1!$C$18
Name iext0: Sheet1!$B$18
Name iext1: Sheet1!$C$18
Name Lambda1: Sheet1!$B$28
Name Lambda2: Sheet1!$B$29
Name m_0: Sheet1!$B$17
Name m_1: Sheet1!$C$17
Name Mi: Sheet1!$B$14
Name money0: Sheet1!$B$17
Name money1: Sheet1!$C$17
Name pbar_0: Sheet1!$B$24
Name pbar_1: Sheet1!$C$24
Name pbar0: Sheet1!$B$24
Name pbar1: Sheet1!$C$24
Name pext_0: Sheet1!$B$20
Name pext_1: Sheet1!$C$20
Name pext0: Sheet1!$B$20
Name pext1: Sheet1!$C$20
Name Psi: Sheet1!$B$10
Name sbar_0: Sheet1!$B$25
Name sbar_1: Sheet1!$C$25
Name sbar0: Sheet1!$B$25
Name sbar1: Sheet1!$C$25
Name Theta: Sheet1!$B$11
Name ypot_0: Sheet1!$B$21
Name ypot_1: Sheet1!$C$21
Name ypot0: Sheet1!$B$21
Name ypot1: Sheet1!$C$21

Sheet Sheet1
A1: EXERCISE 3: Exchange rate overshooting with recurring foreign interest rate shock
E2: Period | F2: p | G2: s | H2: yd | I2: i | J2: i* | K2: ∆p | L2: ∆s | M2: ∆yd | N2: epsilon | O2: z | P2: Z
A3: Endogenous variables | B3: Change over time | E3: 0 | F3: =pbar_0 -> 1.5 | G3: =sbar_0 -> 76.515 | H3: =Beta0_0+Beta1*(G3-F3+pext_0)+(Beta2/Theta)* I3 -> 2000.9 | I3: 3 | J3: =3 *P3 -> 3 | K3: =Mi*(H3-ypot_0) -> 0.009 | L3: =I3-J3 -> 0 | M3: 0 | N3: =Sheet2!A2 -> 0 | O3: =Sheet2!B2 -> 0 | P3: 1
A4: p: Price level | B4: ∆p: Inflation | E4: 1 | F4: =F3+K3 -> 1.509 | G4: =-(m_1-F4-Psi*ypot_1)/(Theta*Lambda1)-iext_1*P4/Lambda1+sbar_1 -> 76.492411 | H4: =Beta0_0+Beta1*(G4-F4+pext_0)+(Beta2/Theta)* I4 -> 2000.2682 | I4: 3 | J4: =3 *P4 -> 3.0012511 | K4: =Mi*(H4-ypot_1) -> 0.0026822527 | L4: =I4-iext_1*P4 -> -0.0012511442 | M4: =(H4-H3) -> -0.63177473 | N4: =Sheet2!A3 -> 0.00041696111 | O4: =Sheet2!B3 -> 0.00041696111 | P4: =EXP(O4) -> 1.000417 | R4: =0.95 -> 0.95
A5: s: Nominal exchange rate | B5: ∆s: Exchange rate depreciation | E5: 2 | F5: =F4+K4 -> 1.5116823 | G5: =-(m_1-F5-Psi*ypot_1)/(Theta*Lambda1)-iext_1*P5/Lambda1+sbar_1 -> 76.517615 | H5: =Beta0_0+Beta1*(G5-F5+pext_0)+(Beta2/Theta)* I5 -> 2000.7187 | I5: 3 | J5: =3 *P5 -> 3.0253034 | K5: =Mi*(H5-ypot_1) -> 0.0071865455 | L5: =I5-iext_1*P5 -> -0.025303433 | M5: =(H5-H4) -> 0.45042927 | N5: =Sheet2!A4 -> 0.0083991062 | O5: =Sheet2!B4 -> 0.0083991062 | P5: =EXP(O5) -> 1.0084345 | R5: 0.01
A6: yd: Aggregate demand | E6: =E5+1 -> 3 | F6: =F5+K5 -> 1.5188688 | G6: =-(m_1-F6-Psi*ypot_1)/(Theta*Lambda1)-iext_1*P6/Lambda1+sbar_1 -> 76.47556 | H6: =Beta0_0+Beta1*(G6-F6+pext_0)+(Beta2/Theta)* I6 -> 1999.7338 | I6: 3 | J6: =3 *P6 -> 3.0084938 | K6: =Mi*(H6-ypot_1) -> -0.0026618302 | L6: =I6-iext_1*P6 -> -0.0084937832 | M6: =(H6-H5) -> -0.98483757 | N6: =Sheet2!A5 -> 0.0028272606 | O6: =Sheet2!B5 -> 0.0028272606 | P6: =EXP(O6) -> 1.0028313
A7: i: Nominal interest rate | E7: =E6+1 -> 4 | F7: =F6+K6 -> 1.516207 | G7: =-(m_1-F7-Psi*ypot_1)/(Theta*Lambda1)-iext_1*P7/Lambda1+sbar_1 -> 76.502669 | H7: =Beta0_0+Beta1*(G7-F7+pext_0)+(Beta2/Theta)* I7 -> 2000.3292 | I7: 3 | J7: =3 *P7 -> 3.0232706 | K7: =Mi*(H7-ypot_1) -> 0.0032923236 | L7: =I7-iext_1*P7 -> -0.02327057 | M7: =(H7-H6) -> 0.59541538 | N7: =Sheet2!A6 -> 0.007726927 | O7: =Sheet2!B6 -> 0.007726927 | P7: =EXP(O7) -> 1.0077569
E8: =E7+1 -> 5 | F8: =F7+K7 -> 1.5194993 | G8: =-(m_1-F8-Psi*ypot_1)/(Theta*Lambda1)-iext_1*P8/Lambda1+sbar_1 -> 76.468625 | H8: =Beta0_0+Beta1*(G8-F8+pext_0)+(Beta2/Theta)* I8 -> 1999.5825 | I8: 3 | J8: =3 *P8 -> 3.0046127 | K8: =Mi*(H8-ypot_1) -> -0.0041749268 | L8: =I8-iext_1*P8 -> -0.0046126876 | M8: =(H8-H7) -> -0.74672504 | N8: =Sheet2!A7 -> 0.0015363817 | O8: =Sheet2!B7 -> 0.0015363817 | P8: =EXP(O8) -> 1.0015376
A9: Parameters | E9: =E8+1 -> 6 | F9: =F8+K8 -> 1.5153244 | G9: =-(m_1-F9-Psi*ypot_1)/(Theta*Lambda1)-iext_1*P9/Lambda1+sbar_1 -> 76.542491 | H9: =Beta0_0+Beta1*(G9-F9+pext_0)+(Beta2/Theta)* I9 -> 2001.1433 | I9: 3 | J9: =3 *P9 -> 3.0510322 | K9: =Mi*(H9-ypot_1) -> 0.011433257 | L9: =I9-iext_1*P9 -> -0.051032203 | M9: =(H9-H8) -> 1.5608184 | N9: =Sheet2!A8 -> 0.016867672 | O9: =Sheet2!B8 -> 0.016867672 | P9: =EXP(O9) -> 1.0170107
A10: Psi | B10: 0.05 | E10: =E9+1 -> 7 | F10: =F9+K9 -> 1.5267576 | G10: =-(m_1-F10-Psi*ypot_1)/(Theta*Lambda1)-iext_1*P10/Lambda1+sbar_1 -> 76.398761 | H10: =Beta0_0+Beta1*(G10-F10+pext_0)+(Beta2/Theta)* I10 -> 1998.0401 | I10: 3 | J10: =3 *P10 -> 2.9673278 | K10: =Mi*(H10-ypot_1) -> -0.01959927 | L10: =I10-iext_1*P10 -> 0.032672212 | M10: =(H10-H9) -> -3.1032527 | N10: =Sheet2!A9 -> -0.010950476 | O10: =Sheet2!B9 -> -0.010950476 | P10: =EXP(O10) -> 0.98910926
A11: Theta | B11: 0.5 | E11: =E10+1 -> 8 | F11: =F10+K10 -> 1.5071584 | G11: =-(m_1-F11-Psi*ypot_1)/(Theta*Lambda1)-iext_1*P11/Lambda1+sbar_1 -> 76.504232 | H11: =Beta0_0+Beta1*(G11-F11+pext_0)+(Beta2/Theta)* I11 -> 2000.5415 | I11: 3 | J11: =3 *P11 -> 3.0063322 | K11: =Mi*(H11-ypot_1) -> 0.005414636 | L11: =I11-iext_1*P11 -> -0.0063322135 | M11: =(H11-H10) -> 2.5013906 | N11: =Sheet2!A10 -> 0.0021085134 | O11: =Sheet2!B10 -> 0.0021085134 | P11: =EXP(O11) -> 1.0021107
A12: Beta1 | B12: 20 | E12: =E11+1 -> 9 | F12: =F11+K11 -> 1.512573 | G12: =-(m_1-F12-Psi*ypot_1)/(Theta*Lambda1)-iext_1*P12/Lambda1+sbar_1 -> 76.475632 | H12: =Beta0_0+Beta1*(G12-F12+pext_0)+(Beta2/Theta)* I12 -> 1999.8612 | I12: 3 | J12: =3 *P12 -> 2.9959562 | K12: =Mi*(H12-ypot_1) -> -0.0013881 | L12: =I12-iext_1*P12 -> 0.0040438292 | M12: =(H12-H11) -> -0.68027359 | N12: =Sheet2!A11 -> -0.0013488523 | O12: =Sheet2!B11 -> -0.0013488523 | P12: =EXP(O12) -> 0.99865206
A13: Beta2 | B13: 0.1 | E13: =E12+1 -> 10 | F13: =F12+K12 -> 1.5111849 | G13: =-(m_1-F13-Psi*ypot_1)/(Theta*Lambda1)-iext_1*P13/Lambda1+sbar_1 -> 76.50107 | H13: =Beta0_0+Beta1*(G13-F13+pext_0)+(Beta2/Theta)* I13 -> 2000.3977 | I13: 3 | J13: =3 *P13 -> 3.0120409 | K13: =Mi*(H13-ypot_1) -> 0.003976962 | L13: =I13-iext_1*P13 -> -0.012040882 | M13: =(H13-H12) -> 0.5365062 | N13: =Sheet2!A12 -> 0.0040055944 | O13: =Sheet2!B12 -> 0.0040055944 | P13: =EXP(O13) -> 1.0040136
A14: Mi | B14: 0.01 | E14: =E13+1 -> 11 | F14: =F13+K13 -> 1.5151618 | G14: =-(m_1-F14-Psi*ypot_1)/(Theta*Lambda1)-iext_1*P14/Lambda1+sbar_1 -> 76.532244 | H14: =Beta0_0+Beta1*(G14-F14+pext_0)+(Beta2/Theta)* I14 -> 2000.9416 | I14: 3 | J14: =3 *P14 -> 3.0431098 | K14: =Mi*(H14-ypot_1) -> 0.0094164766 | L14: =I14-iext_1*P14 -> -0.043109769 | M14: =(H14-H13) -> 0.54395146 | N14: =Sheet2!A13 -> 0.014267654 | O14: =Sheet2!B13 -> 0.014267654 | P14: =EXP(O14) -> 1.0143699
E15: =E14+1 -> 12 | F15: =F14+K14 -> 1.5245783 | G15: =-(m_1-F15-Psi*ypot_1)/(Theta*Lambda1)-iext_1*P15/Lambda1+sbar_1 -> 76.421477 | H15: =Beta0_0+Beta1*(G15-F15+pext_0)+(Beta2/Theta)* I15 -> 1998.538 | I15: 3 | J15: =3 *P15 -> 2.979812 | K15: =Mi*(H15-ypot_1) -> -0.014620317 | L15: =I15-iext_1*P15 -> 0.020187979 | M15: =(H15-H14) -> -2.4036794 | N15: =Sheet2!A14 -> -0.0067520702 | O15: =Sheet2!B14 -> -0.0067520702 | P15: =EXP(O15) -> 0.99327067
A16: Exogenous variables | B16: Initial value | C16: Final value | E16: =E15+1 -> 13 | F16: =F15+K15 -> 1.509958 | G16: =-(m_1-F16-Psi*ypot_1)/(Theta*Lambda1)-iext_1*P16/Lambda1+sbar_1 -> 76.453556 | H16: =Beta0_0+Beta1*(G16-F16+pext_0)+(Beta2/Theta)* I16 -> 1999.472 | I16: 3 | J16: =3 *P16 -> 2.9743569 | K16: =Mi*(H16-ypot_1) -> -0.005280467 | L16: =I16-iext_1*P16 -> 0.025643067 | M16: =(H16-H15) -> 0.93398499 | N16: =Sheet2!A15 -> -0.00858443 | O16: =Sheet2!B15 -> -0.00858443 | P16: =EXP(O16) -> 0.99145231
A17: m: Money supply | B17: 100 | C17: 100 | E17: =E16+1 -> 14 | F17: =F16+K16 -> 1.5046775 | G17: =-(m_1-F17-Psi*ypot_1)/(Theta*Lambda1)-iext_1*P17/Lambda1+sbar_1 -> 76.495298 | H17: =Beta0_0+Beta1*(G17-F17+pext_0)+(Beta2/Theta)* I17 -> 2000.4124 | I17: 3 | J17: =3 *P17 -> 2.9947467 | K17: =Mi*(H17-ypot_1) -> 0.0041240988 | L17: =I17-iext_1*P17 -> 0.0052533184 | M17: =(H17-H16) -> 0.94045659 | N17: =Sheet2!A16 -> -0.0017526411 | O17: =Sheet2!B16 -> -0.0017526411 | P17: =EXP(O17) -> 0.99824889
A18: i*: Foreign nominal interest rate | B18: 3 | C18: 3 | E18: =E17+1 -> 15 | F18: =F17+K17 -> 1.5088016 | G18: =-(m_1-F18-Psi*ypot_1)/(Theta*Lambda1)-iext_1*P18/Lambda1+sbar_1 -> 76.489241 | H18: =Beta0_0+Beta1*(G18-F18+pext_0)+(Beta2/Theta)* I18 -> 2000.2088 | I18: 3 | J18: =3 *P18 -> 2.9985037 | K18: =Mi*(H18-ypot_1) -> 0.0020878599 | L18: =I18-iext_1*P18 -> 0.0014962715 | M18: =(H18-H17) -> -0.20362389 | N18: =Sheet2!A17 -> -0.0004988816 | O18: =Sheet2!B17 -> -0.0004988816 | P18: =EXP(O18) -> 0.99950124
A19: Beta0: Public spending | B19: 500 | C19: 500 | E19: =E18+1 -> 16 | F19: =F18+K18 -> 1.5108895 | G19: =-(m_1-F19-Psi*ypot_1)/(Theta*Lambda1)-iext_1*P19/Lambda1+sbar_1 -> 76.488776 | H19: =Beta0_0+Beta1*(G19-F19+pext_0)+(Beta2/Theta)* I19 -> 2000.1577 | I19: 3 | J19: =3 *P19 -> 3.0023349 | K19: =Mi*(H19-ypot_1) -> 0.0015773446 | L19: =I19-iext_1*P19 -> -0.0023348751 | M19: =(H19-H18) -> -0.051051534 | N19: =Sheet2!A18 -> 0.00077798898 | O19: =Sheet2!B18 -> 0.00077798898 | P19: =EXP(O19) -> 1.0007783
A20: p*: Foreign price level | B20: 0 | C20: 0 | E20: =E19+1 -> 17 | F20: =F19+K19 -> 1.5124668 | G20: =-(m_1-F20-Psi*ypot_1)/(Theta*Lambda1)-iext_1*P20/Lambda1+sbar_1 -> 76.493005 | H20: =Beta0_0+Beta1*(G20-F20+pext_0)+(Beta2/Theta)* I20 -> 2000.2108 | I20: 3 | J20: =3 *P20 -> 3.0086247 | K20: =Mi*(H20-ypot_1) -> 0.0021075361 | L20: =I20-iext_1*P20 -> -0.0086247207 | M20: =(H20-H19) -> 0.053019152 | N20: =Sheet2!A19 -> 0.0028707823 | O20: =Sheet2!B19 -> 0.0028707823 | P20: =EXP(O20) -> 1.0028749
A21: ypot: Potential output | B21: 2000 | C21: 2000 | E21: =E20+1 -> 18 | F21: =F20+K20 -> 1.5145744 | G21: =-(m_1-F21-Psi*ypot_1)/(Theta*Lambda1)-iext_1*P21/Lambda1+sbar_1 -> 76.443211 | H21: =Beta0_0+Beta1*(G21-F21+pext_0)+(Beta2/Theta)* I21 -> 1999.1727 | I21: 3 | J21: =3 *P21 -> 2.9759196 | K21: =Mi*(H21-ypot_1) -> -0.0082726326 | L21: =I21-iext_1*P21 -> 0.024080419 | M21: =(H21-H20) -> -1.0380169 | N21: =Sheet2!A20 -> -0.0080591945 | O21: =Sheet2!B20 -> -0.0080591945 | P21: =EXP(O21) -> 0.99197319
E22: =E21+1 -> 19 | F22: =F21+K21 -> 1.5063017 | G22: =-(m_1-F22-Psi*ypot_1)/(Theta*Lambda1)-iext_1*P22/Lambda1+sbar_1 -> 76.514022 | H22: =Beta0_0+Beta1*(G22-F22+pext_0)+(Beta2/Theta)* I22 -> 2000.7544 | I22: 3 | J22: =3 *P22 -> 3.011878 | K22: =Mi*(H22-ypot_1) -> 0.0075439616 | L22: =I22-iext_1*P22 -> -0.011878012 | M22: =(H22-H21) -> 1.5816594 | N22: =Sheet2!A21 -> 0.0039515198 | O22: =Sheet2!B21 -> 0.0039515198 | P22: =EXP(O22) -> 1.0039593
A23: Steady State | B23: Initial SS | C23: Final SS | E23: =E22+1 -> 20 | F23: =F22+K22 -> 1.5138457 | G23: =-(m_1-F23-Psi*ypot_1)/(Theta*Lambda1)-iext_1*P23/Lambda1+sbar_1 -> 76.53248 | H23: =Beta0_0+Beta1*(G23-F23+pext_0)+(Beta2/Theta)* I23 -> 2000.9727 | I23: 3 | J23: =3 *P23 -> 3.0406525 | K23: =Mi*(H23-ypot_1) -> 0.0097269192 | L23: =I23-iext_1*P23 -> -0.040652532 | M23: =(H23-H22) -> 0.21829576 | N23: =Sheet2!A22 -> 0.013459853 | O23: =Sheet2!B22 -> 0.013459853 | P23: =EXP(O23) -> 1.0135508
A24: p_ee0 | B24: =m_0-Psi*ypot_0+Theta*iext_0 -> 1.5 | C24: =m_1-Psi*ypot_1+Theta*iext_1 -> 1.5 | E24: =E23+1 -> 21 | F24: =F23+K23 -> 1.5235726 | G24: =-(m_1-F24-Psi*ypot_1)/(Theta*Lambda1)-iext_1*P24/Lambda1+sbar_1 -> 76.489696 | H24: =Beta0_0+Beta1*(G24-F24+pext_0)+(Beta2/Theta)* I24 -> 1999.9225 | I24: 3 | J24: =3 *P24 -> 3.0283834 | K24: =Mi*(H24-ypot_1) -> -0.00077526076 | L24: =I24-iext_1*P24 -> -0.02838336 | M24: =(H24-H23) -> -1.050218 | N24: =Sheet2!A23 -> 0.009416644 | O24: =Sheet2!B23 -> 0.009416644 | P24: =EXP(O24) -> 1.0094611
A25: s_ee0 | B25: =m_0-Beta0_0/Beta1-((1-Psi*Beta1)/Beta1)*ypot_0+((Theta*Beta1+Beta2)/Beta1)*iext_0 -> 76.515 | C25: =m_1-Beta0_1/Beta1-((1-Psi*Beta1)/Beta1)*ypot_1+((Theta*Beta1+Beta2)/Beta1)*iext_1 -> 76.515 | E25: =E24+1 -> 22 | F25: =F24+K24 -> 1.5227974 | G25: =-(m_1-F25-Psi*ypot_1)/(Theta*Lambda1)-iext_1*P25/Lambda1+sbar_1 -> 76.43766 | H25: =Beta0_0+Beta1*(G25-F25+pext_0)+(Beta2/Theta)* I25 -> 1998.8972 | I25: 3 | J25: =3 *P25 -> 2.9882493 | K25: =Mi*(H25-ypot_1) -> -0.011027525 | L25: =I25-iext_1*P25 -> 0.011750692 | M25: =(H25-H24) -> -1.0252264 | N25: =Sheet2!A24 -> -0.0039245884 | O25: =Sheet2!B24 -> -0.0039245884 | P25: =EXP(O25) -> 0.9960831
E26: =E25+1 -> 23 | F26: =F25+K25 -> 1.5117698 | G26: =-(m_1-F26-Psi*ypot_1)/(Theta*Lambda1)-iext_1*P26/Lambda1+sbar_1 -> 76.445614 | H26: =Beta0_0+Beta1*(G26-F26+pext_0)+(Beta2/Theta)* I26 -> 1999.2769 | I26: 3 | J26: =3 *P26 -> 2.9720921 | K26: =Mi*(H26-ypot_1) -> -0.0072311718 | L26: =I26-iext_1*P26 -> 0.027907916 | M26: =(H26-H25) -> 0.37963531 | N26: =Sheet2!A25 -> -0.0093461784 | O26: =Sheet2!B25 -> -0.0093461784 | P26: =EXP(O26) -> 0.99069736
A27: Eigenvalues | B27: Real | C27: Imaginary | E27: =E26+1 -> 24 | F27: =F26+K26 -> 1.5045387 | G27: =-(m_1-F27-Psi*ypot_1)/(Theta*Lambda1)-iext_1*P27/Lambda1+sbar_1 -> 76.459455 | H27: =Beta0_0+Beta1*(G27-F27+pext_0)+(Beta2/Theta)* I27 -> 1999.6983 | I27: 3 | J27: =3 *P27 -> 2.9678922 | K27: =Mi*(H27-ypot_1) -> -0.0030167859 | L27: =I27-iext_1*P27 -> 0.032107762 | M27: =(H27-H26) -> 0.42143859 | N27: =Sheet2!A26 -> -0.010760272 | O27: =Sheet2!B26 -> -0.010760272 | P27: =EXP(O27) -> 0.98929741
A28: λ1 | B28: =IF((Beta1*Mi+Beta2*Mi/Theta)^2+4*Beta1*Mi/Theta>0,(-(Beta1*Mi+Beta2*Mi/Theta)-((Beta1*Mi+Beta2*Mi/Theta)^2+4*Beta1*Mi/Theta)^0.5)/2,(-(Beta1*Mi+Beta2*Mi/Theta))/2) -> -0.74146936 | C28: =IF((Beta1*Mi+Beta2*Mi/Theta)^2+4*Beta1*Mi/Theta>0, 0, -SQRT(-(Beta1*Mi+Beta2*Mi/Theta)^2+4*Beta1*Mi/Theta)/2) -> 0 | E28: =E27+1 -> 25 | F28: =F27+K27 -> 1.5015219 | G28: =-(m_1-F28-Psi*ypot_1)/(Theta*Lambda1)-iext_1*P28/Lambda1+sbar_1 -> 76.549072 | H28: =Beta0_0+Beta1*(G28-F28+pext_0)+(Beta2/Theta)* I28 -> 2001.551 | I28: 3 | J28: =3 *P28 -> 3.0283072 | K28: =Mi*(H28-ypot_1) -> 0.015510058 | L28: =I28-iext_1*P28 -> -0.028307246 | M28: =(H28-H27) -> 1.8526844 | N28: =Sheet2!A27 -> 0.0093915101 | O28: =Sheet2!B27 -> 0.0093915101 | P28: =EXP(O28) -> 1.0094357
A29: λ2 | B29: =IF((Beta1*Mi+Beta2*Mi/Theta)^2+4*Beta1*Mi/Theta>0,(-(Beta1*Mi+Beta2*Mi/Theta)+((Beta1*Mi+Beta2*Mi/Theta)^2+4*Beta1*Mi/Theta)^0.5)/2,(-(Beta1*Mi+Beta2*Mi/Theta))/2) -> 0.53946936 | C29: =IF((Beta1*Mi+Beta2*Mi/Theta)^2+4*Beta1*Mi/Theta>0, 0, +SQRT(-(Beta1*Mi+Beta2*Mi/Theta)^2+4*Beta1*Mi/Theta)/2) -> 0 | E29: =E28+1 -> 26 | F29: =F28+K28 -> 1.5170319 | G29: =-(m_1-F29-Psi*ypot_1)/(Theta*Lambda1)-iext_1*P29/Lambda1+sbar_1 -> 76.512811 | H29: =Beta0_0+Beta1*(G29-F29+pext_0)+(Beta2/Theta)* I29 -> 2000.5156 | I29: 3 | J29: =3 *P29 -> 3.0324409 | K29: =Mi*(H29-ypot_1) -> 0.0051558231 | L29: =I29-iext_1*P29 -> -0.032440856 | M29: =(H29-H28) -> -1.0354235 | N29: =Sheet2!A28 -> 0.01075557 | O29: =Sheet2!B28 -> 0.01075557 | P29: =EXP(O29) -> 1.0108136
E30: =E29+1 -> 27 | F30: =F29+K29 -> 1.5221878 | G30: =-(m_1-F30-Psi*ypot_1)/(Theta*Lambda1)-iext_1*P30/Lambda1+sbar_1 -> 76.500089 | H30: =Beta0_0+Beta1*(G30-F30+pext_0)+(Beta2/Theta)* I30 -> 2000.158 | I30: 3 | J30: =3 *P30 -> 3.0333195 | K30: =Mi*(H30-ypot_1) -> 0.0015802381 | L30: =I30-iext_1*P30 -> -0.033319453 | M30: =(H30-H29) -> -0.35755851 | N30: =Sheet2!A29 -> 0.01104526 | O30: =Sheet2!B29 -> 0.01104526 | P30: =EXP(O30) -> 1.0111065
A31: Stability condition | E31: =E30+1 -> 28 | F31: =F30+K30 -> 1.523768 | G31: =-(m_1-F31-Psi*ypot_1)/(Theta*Lambda1)-iext_1*P31/Lambda1+sbar_1 -> 76.458562 | H31: =Beta0_0+Beta1*(G31-F31+pext_0)+(Beta2/Theta)* I31 -> 1999.2959 | I31: 3 | J31: =3 *P31 -> 3.0056889 | K31: =Mi*(H31-ypot_1) -> -0.0070412132 | L31: =I31-iext_1*P31 -> -0.0056889177 | M31: =(H31-H30) -> -0.86214512 | N31: =Sheet2!A30 -> 0.0018945102 | O31: =Sheet2!B30 -> 0.0018945102 | P31: =EXP(O31) -> 1.0018963
A32: Modulus (1+λ1) | B32: =IF(C28=0,ABS(1+B28),SQRT((1+B28)^2+C28^2)) -> 0.25853064 | E32: =E31+1 -> 29 | F32: =F31+K31 -> 1.5167268 | G32: =-(m_1-F32-Psi*ypot_1)/(Theta*Lambda1)-iext_1*P32/Lambda1+sbar_1 -> 76.418194 | H32: =Beta0_0+Beta1*(G32-F32+pext_0)+(Beta2/Theta)* I32 -> 1998.6293 | I32: 3 | J32: =3 *P32 -> 2.9616747 | K32: =Mi*(H32-ypot_1) -> -0.013706601 | L32: =I32-iext_1*P32 -> 0.038325258 | M32: =(H32-H31) -> -0.66653882 | N32: =Sheet2!A31 -> -0.012857389 | O32: =Sheet2!B31 -> -0.012857389 | P32: =EXP(O32) -> 0.98722491
A33: Modulus (1+λ2) | B33: =IF(C29=0,ABS(1+B29),SQRT((1+B29)^2+C29^2)) -> 1.5394694 | E33: =E32+1 -> 30 | F33: =F32+K32 -> 1.5030202 | G33: =-(m_1-F33-Psi*ypot_1)/(Theta*Lambda1)-iext_1*P33/Lambda1+sbar_1 -> 76.464617 | H33: =Beta0_0+Beta1*(G33-F33+pext_0)+(Beta2/Theta)* I33 -> 1999.8319 | I33: 3 | J33: =3 *P33 -> 2.9686828 | K33: =Mi*(H33-ypot_1) -> -0.0016806713 | L33: =I33-iext_1*P33 -> 0.031317193 | M33: =(H33-H32) -> 1.202593 | N33: =Sheet2!A32 -> -0.010493933 | O33: =Sheet2!B32 -> -0.010493933 | P33: =EXP(O33) -> 0.98956094
E35: Volatility | F35: =STDEV(F3:F33) -> 0.0071427189 | G35: =STDEV(G3:G33) -> 0.037211943 | H35: =STDEV(H3:H33) -> 0.81835785 | I35: =STDEV(I3:I33) -> 0 | K35: =STDEV(K3:K33) -> 0.0081835785 | L35: =STDEV(L3:L33) -> 0.024731456 | M35: =STDEV(M3:M33) -> 1.1939726 | N35: =STDEV(N3:N33) -> 0.0082333956 | O35: =STDEV(O3:O33) -> 0.0082333956 | P35: =STDEV(P3:P33) -> 0.0082438185
F36: p | G36: s | H36: yd | I36: i | K36: ∆p | L36: ∆s | M36: ∆yd | N36: epsilon | O36: z | P36: Z

Sheet Sheet2
A1: epsilon | B1: z | C1: Z | E1: rho | F1: 0.99
A2: 0 | B2: 0 | C2: 1 | E2: sigma | F2: 0.01
A3: =NORMINV(RAND(), 0,$F$2) -> 0.00041696111 | B3: =$D$1*B2 + A3 -> 0.00041696111 | C3: =EXP(B3) -> 1.000417
A4: =NORMINV(RAND(), 0,$F$2) -> 0.0083991062 | B4: =$D$1*B3 + A4 -> 0.0083991062 | C4: =EXP(B4) -> 1.0084345
A5: =NORMINV(RAND(), 0,$F$2) -> 0.0028272606 | B5: =$D$1*B4 + A5 -> 0.0028272606 | C5: =EXP(B5) -> 1.0028313
A6: =NORMINV(RAND(), 0,$F$2) -> 0.007726927 | B6: =$D$1*B5 + A6 -> 0.007726927 | C6: =EXP(B6) -> 1.0077569
A7: =NORMINV(RAND(), 0,$F$2) -> 0.0015363817 | B7: =$D$1*B6 + A7 -> 0.0015363817 | C7: =EXP(B7) -> 1.0015376
A8: =NORMINV(RAND(), 0,$F$2) -> 0.016867672 | B8: =$D$1*B7 + A8 -> 0.016867672 | C8: =EXP(B8) -> 1.0170107
A9: =NORMINV(RAND(), 0,$F$2) -> -0.010950476 | B9: =$D$1*B8 + A9 -> -0.010950476 | C9: =EXP(B9) -> 0.98910926
A10: =NORMINV(RAND(), 0,$F$2) -> 0.0021085134 | B10: =$D$1*B9 + A10 -> 0.0021085134 | C10: =EXP(B10) -> 1.0021107
A11: =NORMINV(RAND(), 0,$F$2) -> -0.0013488523 | B11: =$D$1*B10 + A11 -> -0.0013488523 | C11: =EXP(B11) -> 0.99865206
A12: =NORMINV(RAND(), 0,$F$2) -> 0.0040055944 | B12: =$D$1*B11 + A12 -> 0.0040055944 | C12: =EXP(B12) -> 1.0040136
A13: =NORMINV(RAND(), 0,$F$2) -> 0.014267654 | B13: =$D$1*B12 + A13 -> 0.014267654 | C13: =EXP(B13) -> 1.0143699
A14: =NORMINV(RAND(), 0,$F$2) -> -0.0067520702 | B14: =$D$1*B13 + A14 -> -0.0067520702 | C14: =EXP(B14) -> 0.99327067
... A33: =NORMINV(RAND(), 0,$F$2) -> -0.0089021025 | B33: =$D$1*B32 + A33 -> -0.0089021025 | C33: =EXP(B33) -> 0.9911374

Sheet Hoja3
