Workbook

Sheet Model
A1: Simple Dutch Disease Model (3 Sectors)
A2: Editable inputs are blue. Formulas are black. Static assumptions are gray.
A4: Baseline | I4: Resource Boom
A5: Sector | B5: Price (P) | C5: Productivity (A) | D5: Labor (L) | E5: Output (Y=A×L) | F5: Unit Cost (UC=W/A) | G5: Margin (P−UC) | I5: Sector | J5: Price (P) | K5: Productivity (A) | L5: Labor (L) | M5: Output (Y=A×L) | N5: Unit Cost (UC=W/A) | O5: Margin (P−UC)
A6: Manufacturing | B6: 1 | C6: 1 | D6: 30 | E6: =C6*D6 -> 30 | F6: =$B$10/C6 -> 1 | G6: =B6-F6 -> 0 | I6: Manufacturing | J6: 1 | K6: 1 | L6: 20 | M6: =K6*L6 -> 20 | N6: =$J$10/K6 -> 2 | O6: =J6-N6 -> -1
A7: Resources | B7: 1 | C7: 1 | D7: 30 | E7: =C7*D7 -> 30 | F7: =$B$10/C7 -> 1 | G7: =B7-F7 -> 0 | I7: Resources | J7: 1 | K7: 2 | L7: 40 | M7: =K7*L7 -> 80 | N7: =$J$10/K7 -> 1 | O7: =J7-N7 -> 0
A8: Services | B8: =$B$10/C8 -> 1 | C8: 1 | D8: 30 | E8: =C8*D8 -> 30 | F8: =$B$10/C8 -> 1 | G8: =B8-F8 -> 0 | I8: Services | J8: =$J$10/K8 -> 2 | K8: 1 | L8: 30 | M8: =K8*L8 -> 30 | N8: =$J$10/K8 -> 2 | O8: =J8-N8 -> 0
A10: Economy-wide wage (W) | B10: =MAX(B6*C6,B7*C7) -> 1 | C10: Driven by the most productive tradable sector | I10: Economy-wide wage (W) | J10: =MAX(J6*K6,J7*K7) -> 2 | K10: Resource boom raises wages
A12: Change from Baseline to Resource Boom
A13: Variable | B13: Change | C13: Direction | D13: Interpretation | J13: Pct change | K13: Value
A14: Wage (W) | B14: =J10-B10 -> 1 | C14: =IF(B14>0,"Increase",IF(B14<0,"Decrease","No change")) -> Increase | D14: Booming resources sector bids up economy-wide wages. | J14: Wage | K14: =(J10/B10)-1 -> 1
A15: Service price (P_S) | B15: =J8-B8 -> 1 | C15: =IF(B15>0,"Increase",IF(B15<0,"Decrease","No change")) -> Increase | D15: Higher wages make local services more expensive. | J15: Services price | K15: =(J8/B8)-1 -> 1
A16: Manufacturing output | B16: =M6-E6 -> -10 | C16: =IF(B16>0,"Increase",IF(B16<0,"Decrease","No change")) -> Decrease | D16: Manufacturing shrinks as labor moves away and costs rise. | J16: Manuf. output | K16: =(M6/E6)-1 -> -0.33333333
A17: Resource output | B17: =M7-E7 -> 50 | C17: =IF(B17>0,"Increase",IF(B17<0,"Decrease","No change")) -> Increase | D17: Resource sector expands after the productivity shock. | J17: Resource output | K17: =(M7/E7)-1 -> 1.6666667
A18: Manufacturing margin | B18: =O6-G6 -> -1 | C18: =IF(B18>0,"Increase",IF(B18<0,"Decrease","No change")) -> Decrease | D18: Manufacturing becomes less competitive at world prices. | J18: Manuf. margin | K18: =IF(G6=0,"n/a",(O6/G6)-1) -> n/a
A19: Resource margin | B19: =O7-G7 -> 0 | C19: =IF(B19>0,"Increase",IF(B19<0,"Decrease","No change")) -> No change | D19: Resource sector remains profitable at fixed world prices.
A21: Core Equations
A22: 1) Output: Y_i = A_i × L_i
A23: 2) Wage equalization: W = max(P_M×A_M, P_R×A_R)
A24: 3) Tradable prices are fixed internationally: P_M = P_R = 1
A25: 4) Service price is domestic: P_S = W / A_S
A26: 5) Unit cost: UC_i = W / A_i
A27: 6) Dutch disease: a resource boom raises W and P_S, hurting manufacturing competitiveness
A31: Resource Boom Plus Services Expansion: Indirect De-Industrialization
A32: Sector | B32: Price (P) | C32: Productivity (A) | D32: Labor (L) | E32: Output (Y=A×L) | F32: Unit Cost (UC=W/A) | G32: Margin (P−UC)
A33: Manufacturing | B33: 1 | C33: 1 | D33: 10 | E33: =C33*D33 -> 10 | F33: =$J$10/C33 -> 2 | G33: =B33-F33 -> -1
A34: Resources | B34: 1 | C34: 2 | D34: 40 | E34: =C34*D34 -> 80 | F34: =$J$10/C34 -> 1 | G34: =B34-F34 -> 0
A35: Services | B35: =$J$10/C35 -> 2 | C35: 1 | D35: 40 | E35: =C35*D35 -> 40 | F35: =$J$10/C35 -> 2 | G35: =B35-F35 -> 0
A37: Economy-wide wage (W) | B37: =MAX(B33*C33,B34*C34) -> 2 | C37: Resource boom raises wages

Sheet Charts
A1: Dutch Disease Visual Summary
A3: Sector | B3: Baseline Output | C3: Boom Output
A4: Manufacturing | B4: =Model!E6 -> 30 | C4: =Model!M6 -> 20
A5: Resources | B5: =Model!E7 -> 30 | C5: =Model!M7 -> 80
A6: Services | B6: =Model!E8 -> 30 | C6: =Model!M8 -> 30
A10: Variable | B10: Baseline | C10: Boom
A11: Wage | B11: =Model!B10 -> 1 | C11: =Model!J10 -> 2
A12: Service price | B12: =Model!B8 -> 1 | C12: =Model!J8 -> 2
A13: Manufacturing unit cost | B13: =Model!F6 -> 1 | C13: =Model!N6 -> 2

Sheet Guide
A1: How to use this workbook
A3: 1. Change productivity and labor allocations in the blue cells.
A4: 2. Manufacturing and resources are tradable sectors with world prices normalized to 1.
A5: 3. Services are non-tradable, so their price adjusts domestically as P_S = W / A_S.
A6: 4. The common wage is pinned down by the most productive tradable sector.
A7: 5. A resource boom raises wages and the services price, squeezing manufacturing.
A8: 6. Try changing A_R, A_S, or labor allocations to see stronger or weaker Dutch disease effects.
